invitro/__init__.py
invitro/invitro.py
invitro-0.0.0.dist-info/METADATA
invitro-0.0.0.dist-info/WHEEL
invitro-0.0.0.dist-info/top_level.txt
invitro-0.0.0.dist-info/RECORD
