Metadata-Version: 2.1
Name: invitro
Version: 0.0.0
Summary: Coming Soon
Author: Cedric H
Author-email: a.asaf.lk@gmail.com
Requires-Dist: numpy
Requires-Dist: pandas
